rmi/__init__.py
rmi/rmi.py
rmi_pytorch-0.1.1.dist-info/LICENSE
rmi_pytorch-0.1.1.dist-info/METADATA
rmi_pytorch-0.1.1.dist-info/WHEEL
rmi_pytorch-0.1.1.dist-info/top_level.txt
rmi_pytorch-0.1.1.dist-info/RECORD
