Metadata-Version: 2.1
Name: rmi-pytorch
Version: 0.1.1
Summary: Region Mutual Information loss in PyTorch
Home-page: https://github.com/RElbers/region-mutual-information-pytorch
Author: Robin Elbers
Author-email: UNKNOWN
License: MIT
Platform: UNKNOWN
Requires-Dist: torch
